classdiagramgen/__init__.py
classdiagramgen/class_diagram.py
classdiagramgen/csharp_analyser.py
classdiagramgen/utils.py
class_diagram_generator-2.0.10.dist-info/LICENSE
class_diagram_generator-2.0.10.dist-info/METADATA
class_diagram_generator-2.0.10.dist-info/WHEEL
class_diagram_generator-2.0.10.dist-info/top_level.txt
class_diagram_generator-2.0.10.dist-info/RECORD
