Metadata-Version: 2.1
Name: class-diagram-generator
Version: 2.0.10
Summary: Generate standardized class diagrams based on C# source code
Home-page: https://github.com/RokasPuzonas/class-diagram-generator
Author: Rokas Puzonas
Author-email: rokas.puz@gmail.com
License: GNU GPLv2
Project-URL: Source Code, https://github.com/RokasPuzonas/class-diagram-generator
Platform: UNKNOWN
Classifier: Programming Language :: Python :: 3
Classifier: Topic :: Utilities
Classifier: Intended Audience :: Developers
Requires-Python: >=3.10
License-File: LICENSE
Requires-Dist: lark
Requires-Dist: Pillow
